tollbit/__init__.py
tollbit/_apis/__init__.py
tollbit/_apis/content_api.py
tollbit/_apis/content_retrieval_api.py
tollbit/_apis/errors.py
tollbit/_apis/models/README.md
tollbit/_apis/models/__init__.py
tollbit/_apis/models/_generated/__init__.py
tollbit/_apis/models/_generated/openapi_tollbit_apis.py
tollbit/_apis/models/_hand_rolled/__init__.py
tollbit/_apis/models/api_base.py
tollbit/_apis/search_api.py
tollbit/_apis/self_reporting_api.py
tollbit/_apis/token_api.py
tollbit/_environment.py
tollbit/_logging.py
tollbit/content_formats.py
tollbit/crawl_content/__init__.py
tollbit/crawl_content/client.py
tollbit/currencies.py
tollbit/forgiving_urls.py
tollbit/licenses/__init__.py
tollbit/licenses/permissions.py
tollbit/licenses/types.py
tollbit/py.typed
tollbit/search/__init__.py
tollbit/search/client.py
tollbit/self_reporting/__init__.py
tollbit/self_reporting/client.py
tollbit/self_reporting/usage.py
tollbit/tokens.py
tollbit/use_content/__init__.py
tollbit/use_content/client.py
tollbit/use_content/types.py
tollbit_python_sdk-0.5.2.dist-info/METADATA
tollbit_python_sdk-0.5.2.dist-info/WHEEL
tollbit_python_sdk-0.5.2.dist-info/licenses/LICENSE
tollbit_python_sdk-0.5.2.dist-info/RECORD
