Metadata-Version: 2.4
Name: tollbit-python-sdk
Version: 0.5.2
Summary: Tollbit SDK for interacting tollbit services, including retrieving content and connecting to the API
License: MIT
License-File: LICENSE
Author: Tollbit
Author-email: team@tollbit.com
Requires-Python: >=3.10,<4.0
Classifier: Programming Language :: Python :: 3
Classifier: Programming Language :: Python :: 3.10
Classifier: Programming Language :: Python :: 3.11
Classifier: Programming Language :: Python :: 3.12
Classifier: Typing :: Typed
Requires-Dist: anyio (>=4.12.0,<5.0.0)
Requires-Dist: httpx (>=0.28.1,<0.29.0)
Requires-Dist: pydantic (>=2.8,<3.0)
Requires-Dist: python-dateutil (>=2.9.0.post0,<3.0.0)
Requires-Dist: python-json-logger (>=4.0.0,<5.0.0)
Requires-Dist: requests (>=2.32.5,<3.0.0)
Project-URL: Documentation, https://github.com/tollbit/tollbit-python-sdk#readme
Project-URL: Homepage, https://tollbit.com
Project-URL: Repository, https://github.com/tollbit/tollbit-python-sdk
